helios_solc/__init__.py
helios_solc/exceptions.py
helios_solc/install.py
helios_solc/main.py
helios_solc/wrapper.py
helios_solc/utils/__init__.py
helios_solc/utils/filesystem.py
helios_solc/utils/string.py
helios_solc/utils/types.py
py_helios_solc-3.2.2.dist-info/LICENSE
py_helios_solc-3.2.2.dist-info/METADATA
py_helios_solc-3.2.2.dist-info/WHEEL
py_helios_solc-3.2.2.dist-info/top_level.txt
py_helios_solc-3.2.2.dist-info/RECORD
