Metadata-Version: 2.1
Name: py-helios-solc
Version: 3.2.2
Summary: Python wrapper around the helios solc binary
Home-page: https://github.com/Helios-Protocol/py-helios-solc
Author: Tommy Mckinnon
Author-email: tommy@heliosprotocol.io
License: MIT
Keywords: ethereum helios protocol solidity solc
Platform: UNKNOWN
Classifier: Intended Audience :: Developers
Classifier: License :: OSI Approved :: MIT License
Classifier: Natural Language :: English
Classifier: Programming Language :: Python :: 2
Classifier: Programming Language :: Python :: 2.7
Classifier: Programming Language :: Python :: 3
Classifier: Programming Language :: Python :: 3.4
Classifier: Programming Language :: Python :: 3.5
Requires-Python: >=3.4, <4
Requires-Dist: semantic-version (>=2.6.0)
